brevia/__init__.py
brevia/alembic/README
brevia/alembic/__init__.py
brevia/alembic/env.py
brevia/alembic/script.py.mako
brevia/alembic/versions/1d927e0cbc61_locked_until_column.py
brevia/alembic/versions/1eab976dea29_initial_schema.py
brevia/alembic/versions/24b025d48e0a_config_table.py
brevia/alembic/versions/95d93297832c_migration_to_jsonb_format.py
brevia/alembic/versions/b34017752e45_chat_history_evaluation.py
brevia/alembic/versions/be67c72a4e5a_async_jobs_table.py
brevia/alembic/versions/eb659f4dd1c9_utc_timestamp.py
brevia/async_jobs.py
brevia/base_retriever.py
brevia/callback.py
brevia/chat_history.py
brevia/collections.py
brevia/commands.py
brevia/completions.py
brevia/connection.py
brevia/dependencies.py
brevia/events.py
brevia/extensions/__init__.py
brevia/index.py
brevia/load_file.py
brevia/middleware.py
brevia/models.py
brevia/postman/Brevia API.postman_collection.json
brevia/postman/Brevia API.postman_environment.json
brevia/prompts/rag/condense.yml
brevia/prompts/rag/human.yml
brevia/prompts/rag/system.yml
brevia/prompts/text_analysis/questions_initial.yml
brevia/prompts/text_analysis/questions_refine.yml
brevia/prompts.py
brevia/providers.py
brevia/query.py
brevia/routers/__init__.py
brevia/routers/analyze_router.py
brevia/routers/app_routers.py
brevia/routers/audio_router.py
brevia/routers/chat_history_router.py
brevia/routers/collections_router.py
brevia/routers/completion_router.py
brevia/routers/config_router.py
brevia/routers/download_router.py
brevia/routers/index_router.py
brevia/routers/jobs_router.py
brevia/routers/providers_router.py
brevia/routers/qa_router.py
brevia/routers/status_router.py
brevia/services.py
brevia/settings.py
brevia/tasks/__init__.py
brevia/tasks/base.py
brevia/tasks/text_analysis.py
brevia/tokens.py
brevia/utilities/__init__.py
brevia/utilities/collections_io.py
brevia/utilities/dates.py
brevia/utilities/files_import.py
brevia/utilities/json_api.py
brevia/utilities/openapi.py
brevia/utilities/output.py
brevia-0.15.2.dist-info/METADATA
brevia-0.15.2.dist-info/WHEEL
brevia-0.15.2.dist-info/entry_points.txt
brevia-0.15.2.dist-info/licenses/LICENSE
brevia-0.15.2.dist-info/RECORD
