Metadata-Version: 2.4
Name: Brevia
Version: 0.15.2
Summary: Extensible API and framework to build your Retrieval Augmented Generation (RAG) and Information Extraction (IE) applications with LLMs
License-File: LICENSE
Author: Niki Corradetti
Author-email: niki.corradetti@atlasconsulting.it
Requires-Python: >=3.10,<3.14
Classifier: Programming Language :: Python :: 3
Classifier: Programming Language :: Python :: 3.10
Classifier: Programming Language :: Python :: 3.11
Classifier: Programming Language :: Python :: 3.12
Classifier: Programming Language :: Python :: 3.13
Requires-Dist: alembic (>=1.11.1,<2.0.0)
Requires-Dist: bs4 (>=0.0.1,<0.0.2)
Requires-Dist: fastapi (>=0.115.12,<0.116.0)
Requires-Dist: glom (>=24.11.0,<25.0.0)
Requires-Dist: jinja2 (>=3.1.4,<4.0.0)
Requires-Dist: langchain (>=0.3.20,<0.4.0)
Requires-Dist: langchain-anthropic (>=0.3.9,<0.4.0)
Requires-Dist: langchain-cohere (>=0.4.2,<0.5.0)
Requires-Dist: langchain-community (>=0.3.19,<0.4.0)
Requires-Dist: langchain-deepseek (>=0.1.2,<0.2.0)
Requires-Dist: langchain-ollama (>=0.2.3,<0.3.0)
Requires-Dist: langchain-openai (>=0.3.7,<0.4.0)
Requires-Dist: lxml (>=5.3.1,<6.0.0)
Requires-Dist: nltk (>=3.9.1,<4.0.0)
Requires-Dist: pgvector (>=0.4.0,<0.5.0)
Requires-Dist: psycopg2-binary (>=2.9.10,<3.0.0)
Requires-Dist: pydantic-settings (>=2.1.0,<3.0.0)
Requires-Dist: pypdf (>=5.4.0,<6.0.0)
Requires-Dist: python-dotenv (>=1.0.0,<2.0.0)
Requires-Dist: python-jose (>=3.3.0,<4.0.0)
Requires-Dist: python-multipart (>=0.0.20,<0.0.21)
Requires-Dist: sqlalchemy-utils (>=0.41.1,<0.42.0)
Requires-Dist: tomli (>=2.0.1,<3.0.0)
Requires-Dist: uvicorn[standard] (>=0.34.2,<0.35.0)
Project-URL: Homepage, https://github.com/brevia-ai/brevia
Project-URL: Repository, https://github.com/brevia-ai/brevia
